news_crawlers/__init__.py
news_crawlers/__main__.py
news_crawlers/configuration.py
news_crawlers/news_crawlers.yaml
news_crawlers/notificators.py
news_crawlers/scheduler.py
news_crawlers/scrape.py
news_crawlers/spiders.py
news_crawlers/news_crawlers.egg-info/PKG-INFO
news_crawlers/news_crawlers.egg-info/SOURCES.txt
news_crawlers/news_crawlers.egg-info/dependency_links.txt
news_crawlers/news_crawlers.egg-info/requires.txt
news_crawlers/news_crawlers.egg-info/top_level.txt
news_crawlers-3.5.1.dist-info/LICENSE.txt
news_crawlers-3.5.1.dist-info/METADATA
news_crawlers-3.5.1.dist-info/WHEEL
news_crawlers-3.5.1.dist-info/entry_points.txt
news_crawlers-3.5.1.dist-info/top_level.txt
news_crawlers-3.5.1.dist-info/RECORD
