Metadata-Version: 2.1
Name: news-crawlers
Version: 3.5.1
Summary: An extensible python library to create web crawlers which alert users on news.
Author-email: Jost Prevc <jost.prevc@gmail.com>
License: MIT
Keywords: crawler,news
Classifier: Programming Language :: Python :: 3
Requires-Python: >=3.7
License-File: LICENSE.txt
Requires-Dist: beautifulsoup4
Requires-Dist: pydantic
Requires-Dist: PyYAML
Requires-Dist: requests
Requires-Dist: schedule
Requires-Dist: importlib-metadata
Provides-Extra: dev
Requires-Dist: pytest ; extra == 'dev'
Requires-Dist: pylint ; extra == 'dev'
Requires-Dist: pre-commit ; extra == 'dev'
Requires-Dist: black[d] ; extra == 'dev'
Requires-Dist: mypy ; extra == 'dev'
Requires-Dist: tox ; extra == 'dev'
Requires-Dist: types-beautifulsoup4 ; extra == 'dev'
Requires-Dist: types-requests ; extra == 'dev'
Requires-Dist: types-PyYAML ; extra == 'dev'
Provides-Extra: test
Requires-Dist: pytest ; extra == 'test'
